MANIFEST.in
setup.py
pybs/__init__.py
pybs.egg-info/PKG-INFO
pybs.egg-info/SOURCES.txt
pybs.egg-info/dependency_links.txt
pybs.egg-info/not-zip-safe
pybs.egg-info/requires.txt
pybs.egg-info/top_level.txt