Metadata-Version: 1.1
Name: pybs
Version: 0.3
Summary: A library for computing with trees and B-series
Home-page: http://github.com/henriksu/pybs
Author: Henrik Sperre Sundklakk
Author-email: henrik.sundklakk@gmail.com
License: UNKNOWN
Keywords: B-series rooted tree trees Butcher
Platform: UNKNOWN
Classifier: Programming Language :: Python :: 2.7
Classifier: Intended Audience :: Science/Research
Classifier: Topic :: Scientific/Engineering :: Mathematics 
